NetworkStatisticsService/__init__.py
NetworkStatisticsService/command_line_utils.py
NetworkStatisticsService/dynamo_db_config.py
NetworkStatisticsService/dynamodb_statistics_uploader.py
NetworkStatisticsService/exceptions.py
NetworkStatisticsService/informal_statistics_uploader.py
NetworkStatisticsService/latency_statistic_utils.py
NetworkStatisticsService/speed_statistic_utils.py
NetworkStatisticsService/statistics_service.py
NetworkStatisticsService/string_utils.py
NetworkStatisticsService/time_utils.py
NetworkStatisticsService/ttl_config.py
network_statistics_service-1.0.4.dist-info/LICENSE
network_statistics_service-1.0.4.dist-info/METADATA
network_statistics_service-1.0.4.dist-info/WHEEL
network_statistics_service-1.0.4.dist-info/top_level.txt
network_statistics_service-1.0.4.dist-info/RECORD
