Metadata-Version: 2.1
Name: network-statistics-service
Version: 1.0.4
Summary: Package for generating network statistics such as latency and download speed.
Home-page: https://gitlab.com/stefan.georgescu/network-statistics-service
Author: Stefan Georgescu
Author-email: contact@stefangeorgescu.com
License: MIT
Platform: UNKNOWN
Classifier: Programming Language :: Python :: 3
Classifier: License :: OSI Approved :: MIT License
Classifier: Operating System :: OS Independent
Requires-Python: >=3.5
Requires-Dist: speedtest-cli
